yt_dlp_plugins/postprocessor/stash.py
yt_dlp_stash-2.0.0.dist-info/licenses/LICENSE
yt_dlp_stash-2.0.0.dist-info/METADATA
yt_dlp_stash-2.0.0.dist-info/WHEEL
yt_dlp_stash-2.0.0.dist-info/top_level.txt
yt_dlp_stash-2.0.0.dist-info/RECORD
