Metadata-Version: 2.4
Name: yt-dlp-stash
Version: 2.0.0
Author-email: Schmoaaaaah <schmoaaaaah@r4nd0.com>
License:                     GNU AFFERO GENERAL PUBLIC LICENSE
Requires-Python: >=3.11
License-File: LICENSE
Requires-Dist: yt-dlp>=2025.03.31
Requires-Dist: stashapp-tools>=0.2.58
Dynamic: license-file
